<Configuration type='cctv'>
    <header>
        <cctv>IF-065-1</cctv>
        <version>1</version>
        <date>2021/09/28 19:01:00</date>
        <intersection_id>IF-065</intersection_id>
        <device_ip>192.168.0.1</device_ip>
        <camera_position>
            <lat>24.7812538</lat>
            <lng>120.9970594</lng>
        </camera_position>
    </header>
    <road_information>
        <Reference_points>
            <point>
                <img_x>263</img_x>
                <img_y>316</img_y>
                <lat>24.781107</lat>
                <lng>120.997274</lng>
            </point>
            <point>
                <img_x>1350</img_x>
                <img_y>284</img_y>
                <lat>24.781132</lat>
                <lng>120.997058</lng>
            </point>
        </Reference_points>
    </road_information>
    <virtual_gate>
        <road>
            <road_id>1</road_id>
            <link_id>3001900107029Q</link_id>
            <direction>Out</direction>
            <position>
                <x1>150</x1>
                <y1>492</y1>
                <x2>835</x2>
                <y2>458</y2>
            </position>
            <lanes>
                <lane>
                    <lane_id>1</lane_id>
                    <position>
                        <x1>595</x1>
                        <y1>578</y1>
                        <x2>835</x2>
                        <y2>458</y2>
                    </position>
                </lane>
                <lane>
                    <lane_id>2</lane_id>
                    <position>
                        <x1>835</x1>
                        <y1>458</y1>
                        <x2>357</x2>
                        <y2>495</y2>
                    </position>
                </lane>
            </lanes>
        </road>
        <road>
            <road_id>2</road_id>
            <link_id>4016400001675Q</link_id>
            <direction>In</direction>       
            <position>
                <x1>107</x1>
                <y1>327</y1>
                <x2>168</x2>
                <y2>280</y2>
            </position>
            <lanes>
                <lane>
                    <lane_id>1</lane_id>
                    <ForwardDirection>0010</ForwardDirection>
                    <position>
                        <x1>2595</x1>
                        <y1>2578</y1>
                        <x2>2835</x2>
                        <y2>2458</y2>
                    </position>
                </lane>
                <lane>
                    <lane_id>2</lane_id>
                    <ForwardDirection>0010</ForwardDirection>
                    <position>
                        <x1>835</x1>
                        <y1>458</y1>
                        <x2>357</x2>
                        <y2>495</y2>
                    </position>
                </lane>
            </lanes>
        </road>
        <road>
            <road_id>3</road_id>
            <link_id>4016400001675Q</link_id>
            <direction>Out</direction>
            <position>
                <x1>168</x1>
                <y1>280</y1>
                <x2>222</x2>
                <y2>248</y2>
            </position>
            <lanes>
                <lane>
                    <lane_id>1</lane_id>
                    <position>
                        <x1>595</x1>
                        <y1>578</y1>
                        <x2>835</x2>
                        <y2>458</y2>
                    </position>
                </lane>
                <lane>
                    <lane_id>2</lane_id>
                    <position>
                        <x1>835</x1>
                        <y1>458</y1>
                        <x2>357</x2>
                        <y2>495</y2>
                    </position>
                </lane>
            </lanes>
        </road>
        <road>
            <road_id>4</road_id>
            <link_id>3001900107078Q</link_id>
            <direction>In</direction>
            <position>
                <x1>386</x1>
                <y1>194</y1>
                <x2>682</x2>
                <y2>170</y2>
            </position>
            <lanes>
                <lane>
                    <lane_id>1</lane_id>
                    <ForwardDirection>1000</ForwardDirection>
                    <position>
                        <x1>682</x1>
                        <y1>170</y1>
                        <x2>578</x2>
                        <y2>178</y2>
                    </position>
                </lane>
                <lane>
                    <lane_id>2</lane_id>
                    <ForwardDirection>1100</ForwardDirection>
                    <position>
                        <x1>578</x1>
                        <y1>178</y1>
                        <x2>486</x2>
                        <y2>186</y2>
                    </position>
                </lane>
            </lanes>
        </road>
        <road>
            <road_id>5</road_id>
            <link_id>3001900007078Q</link_id>
            <direction>Out</direction>
            <position>
                <x1>7445</x1>
                <y1>1695</y1>
                <x2>9985</x2>
                <y2>1415</y2>
            </position>
            <lanes>
                <lane>
                    <lane_id>1</lane_id>
                    <position>
                        <x1>5682</x1>
                        <y1>5170</y1>
                        <x2>5578</x2>
                        <y2>5178</y2>
                    </position>
                </lane>
            </lanes>
        </road>
        <road>
            <road_id>6</road_id>
            <link_id>3001900007029Q</link_id>
            <direction>In</direction>
            <position>
                <x1>69926</x1>
                <y1>65056</y1>
                <x2>616556</x2>
                <y2>64396</y2>
            </position>
            <lanes>
                <lane>
                    <lane_id>1</lane_id>
                    <ForwardDirection>1000</ForwardDirection>
                    <position>
                        <x1>6682</x1>
                        <y1>6170</y1>
                        <x2>6578</x2>
                        <y2>6178</y2>
                    </position>
                </lane>
            </lanes>
        </road>
    </virtual_gate>
</Configuration>